setup.cfg
setup.py
elastictex/__init__.py
elastictex/api.py
elastictex/crawl.py
elastictex/server.py
elastictex.egg-info/PKG-INFO
elastictex.egg-info/SOURCES.txt
elastictex.egg-info/dependency_links.txt
elastictex.egg-info/entry_points.txt
elastictex.egg-info/requires.txt
elastictex.egg-info/top_level.txt
elastictex/templates/index.html
mongo_connector/__init__.py
mongo_connector/doc_managers/__init__.py
mongo_connector/doc_managers/elastictex_doc_manager.py