Metadata-Version: 1.0
Name: elastictex
Version: 0.1.3
Summary: Search with Latex
Home-page: http://github.com/xmasotto/elastictex
Author: Xander Masotto
Author-email: xmasotto@gmail.com
License: UNKNOWN
Platform: UNKNOWN
